.gitignore
MANIFEST.in
changelog.md
pyproject.toml
readme.md
release.md
setup.py
.github/workflows/test.yml
docs/Makefile
docs/conf.py
docs/index.md
docs/requirements.txt
docs/guide/coordinates.md
docs/guide/images.md
docs/guide/installation.md
docs/guide/labels.md
docs/guide/meshes.md
docs/guide/visualization.md
docs/reference/affine.rst
docs/reference/geometry.rst
docs/reference/image.rst
docs/reference/io.rst
docs/reference/mesh.rst
docs/reference/system.rst
docs/reference/visualization.rst
docs/static/logo-bg-hover.svg
docs/static/logo-bg.svg
docs/static/style.css
docs/templates/autosummary/class.rst
surfa/__init__.py
surfa/freesurfer.py
surfa/pipeline.py
surfa/system.py
surfa.egg-info/PKG-INFO
surfa.egg-info/SOURCES.txt
surfa.egg-info/dependency_links.txt
surfa.egg-info/requires.txt
surfa.egg-info/top_level.txt
surfa/core/__init__.py
surfa/core/array.py
surfa/core/framed.py
surfa/core/istype.py
surfa/core/labels.py
surfa/core/slicing.py
surfa/image/__init__.py
surfa/image/framed.py
surfa/image/interp.pyx
surfa/io/__init__.py
surfa/io/affine.py
surfa/io/framed.py
surfa/io/fsio.py
surfa/io/fsnifti1extension.py
surfa/io/labels.py
surfa/io/mesh.py
surfa/io/protocol.py
surfa/io/timeseries.py
surfa/io/utils.py
surfa/mesh/__init__.py
surfa/mesh/cache.py
surfa/mesh/distance.py
surfa/mesh/intersection.h
surfa/mesh/intersection.pyx
surfa/mesh/mesh.py
surfa/mesh/overlay.py
surfa/mesh/sphere.py
surfa/mesh/timeseries.py
surfa/transform/__init__.py
surfa/transform/affine.py
surfa/transform/geometry.py
surfa/transform/orientation.py
surfa/transform/space.py
surfa/transform/warp.py
surfa/vis/__init__.py
surfa/vis/freeview.py
test/test_framed.py