Metadata-Version: 2.1
Name: surfa
Version: 0.6.3
Summary: Utilities for medical image and surface processing.
Home-page: https://github.com/freesurfer/surfa
Author: Andrew Hoopes
Author-email: freesurfer@nmr.mgh.harvard.edu
Classifier: Development Status :: 3 - Alpha
Classifier: License :: OSI Approved :: MIT License
Classifier: Programming Language :: Python :: 3
Classifier: Natural Language :: English
Classifier: Topic :: Scientific/Engineering
Requires-Python: >=3.6
